RnDNews/DuckDuckGo_Scraper.py
RnDNews/Google_Scraper.py
RnDNews/Scraper.py
RnDNews/Shared_Methods.py
RnDNews/__init__.py
RnDNews/config.py
RnDNews-0.1.6.dist-info/METADATA
RnDNews-0.1.6.dist-info/WHEEL
RnDNews-0.1.6.dist-info/top_level.txt
RnDNews-0.1.6.dist-info/RECORD
